[{"version_details":[{"max_chance":20,"version":{"url":"http:\/\/127.0.0.1:8000\/api\/v2\/version\/17\/","name":"black"},"encounter_details":[{"min_level":58,"max_level":58,"condition_values":[],"chance":10,"method":{"url":"http:\/\/127.0.0.1:8000\/api\/v2\/encounter-method\/8\/","name":"dark-grass"}},{"min_level":60,"max_level":60,"condition_values":[],"chance":10,"method":{"url":"http:\/\/127.0.0.1:8000\/api\/v2\/encounter-method\/8\/","name":"dark-grass"}}]}],"location_area":{"url":"http:\/\/127.0.0.1:8000\/api\/v2\/location-area\/621\/","name":"village-bridge-area"}},{"version_details":[{"max_chance":25,"version":{"url":"http:\/\/127.0.0.1:8000\/api\/v2\/version\/17\/","name":"black"},"encounter_details":[{"min_level":58,"max_level":58,"condition_values":[],"chance":20,"method":{"url":"http:\/\/127.0.0.1:8000\/api\/v2\/encounter-method\/8\/","name":"dark-grass"}},{"min_level":60,"max_level":60,"condition_values":[],"chance":4,"method":{"url":"http:\/\/127.0.0.1:8000\/api\/v2\/encounter-method\/8\/","name":"dark-grass"}},{"min_level":60,"max_level":60,"condition_values":[],"chance":1,"method":{"url":"http:\/\/127.0.0.1:8000\/api\/v2\/encounter-method\/8\/","name":"dark-grass"}}]}],"location_area":{"url":"http:\/\/127.0.0.1:8000\/api\/v2\/location-area\/645\/","name":"unova-route-11-area"}}]
